lib/melcloud/__init__.py
lib/melcloud/devices.py
lib/melcloud/helpers.py
lib/melcloud/jsongenerator.py
lib/melcloud/melcloudclient.py
melcloudlibasyncio-1.1.1.dist-info/METADATA
melcloudlibasyncio-1.1.1.dist-info/WHEEL
melcloudlibasyncio-1.1.1.dist-info/RECORD
