Metadata-Version: 2.1
Name: melcloudlibasyncio
Version: 1.1.1
Summary: A async client for interacting with the MELCloud API
License: MIT
Author: Simen Andrè Skogum
Author-email: v0nNemize@gmail.com
Requires-Python: >=3.8,<4.0
Classifier: License :: OSI Approved :: MIT License
Classifier: Programming Language :: Python :: 3
Classifier: Programming Language :: Python :: 3.8
Classifier: Programming Language :: Python :: 3.9
Classifier: Programming Language :: Python :: 3.10
Classifier: Programming Language :: Python :: 3.11
Classifier: Programming Language :: Python :: 3.12
Requires-Dist: aiohttp (>=3.10.5,<4.0.0)
Requires-Dist: mkdocs (>=1.6.1,<2.0.0)
